{
    "drinks": [
        {
            "strDrink": "1-900-FUK-MEUP",
            "strDrinkThumb": "https:\/\/www.thecocktaildb.com\/images\/media\/drink\/uxywyw1468877224.jpg",
            "idDrink": "15395"
        },
        {
            "strDrink": "110 in the shade",
            "strDrinkThumb": "https:\/\/www.thecocktaildb.com\/images\/media\/drink\/xxyywq1454511117.jpg",
            "idDrink": "15423"
        },
        {
            "strDrink": "151 Florida Bushwacker",
            "strDrinkThumb": "https:\/\/www.thecocktaildb.com\/images\/media\/drink\/rvwrvv1468877323.jpg",
            "idDrink": "14588"
        },
        {
            "strDrink": "155 Belmont",
            "strDrinkThumb": "https:\/\/www.thecocktaildb.com\/images\/media\/drink\/yqvvqs1475667388.jpg",
            "idDrink": "15346"
        },
        {
            "strDrink": "24k nightmare",
            "strDrinkThumb": "https:\/\/www.thecocktaildb.com\/images\/media\/drink\/yyrwty1468877498.jpg",
            "idDrink": "17060"
        },
        {
            "strDrink": "252",
            "strDrinkThumb": "https:\/\/www.thecocktaildb.com\/images\/media\/drink\/rtpxqw1468877562.jpg",
            "idDrink": "15288"
        },
        {
            "strDrink": "3 Wise Men",
            "strDrinkThumb": "https:\/\/www.thecocktaildb.com\/images\/media\/drink\/wxqpyw1468877677.jpg",
            "idDrink": "13899"
        },
        {
            "strDrink": "3-Mile Long Island Iced Tea",
            "strDrinkThumb": "https:\/\/www.thecocktaildb.com\/images\/media\/drink\/rrtssw1472668972.jpg",
            "idDrink": "15300"
        },
        {
            "strDrink": "410 Gone",
            "strDrinkThumb": "https:\/\/www.thecocktaildb.com\/images\/media\/drink\/xtuyqv1472669026.jpg",
            "idDrink": "13581"
        },
        {
            "strDrink": "50\/50",
            "strDrinkThumb": "https:\/\/www.thecocktaildb.com\/images\/media\/drink\/wwpyvr1461919316.jpg",
            "idDrink": "14598"
        },
        {
            "strDrink": "501 Blue",
            "strDrinkThumb": "https:\/\/www.thecocktaildb.com\/images\/media\/drink\/ywxwqs1461867097.jpg",
            "idDrink": "17105"
        },
        {
            "strDrink": "57 Chevy with a White License Plate",
            "strDrinkThumb": "https:\/\/www.thecocktaildb.com\/images\/media\/drink\/qyyvtu1468878544.jpg",
            "idDrink": "14029"
        },
        {
            "strDrink": "69 Special",
            "strDrinkThumb": "https:\/\/www.thecocktaildb.com\/images\/media\/drink\/vqyxqx1472669095.jpg",
            "idDrink": "13940"
        },
        {
            "strDrink": "747",
            "strDrinkThumb": "https:\/\/www.thecocktaildb.com\/images\/media\/drink\/xxsxqy1472668106.jpg",
            "idDrink": "14229"
        },
        {
            "strDrink": "747 Drink",
            "strDrinkThumb": "https:\/\/www.thecocktaildb.com\/images\/media\/drink\/i9suxb1582474926.jpg",
            "idDrink": "178318"
        },
        {
            "strDrink": "9 1\/2 Weeks",
            "strDrinkThumb": "https:\/\/www.thecocktaildb.com\/images\/media\/drink\/xvwusr1472669302.jpg",
            "idDrink": "16108"
        },
        {
            "strDrink": "A Day at the Beach",
            "strDrinkThumb": "https:\/\/www.thecocktaildb.com\/images\/media\/drink\/trptts1454514474.jpg",
            "idDrink": "15200"
        },
        {
            "strDrink": "A Furlong Too Late",
            "strDrinkThumb": "https:\/\/www.thecocktaildb.com\/images\/media\/drink\/ssxvww1472669166.jpg",
            "idDrink": "17831"
        },
        {
            "strDrink": "A Gilligan's Island",
            "strDrinkThumb": "https:\/\/www.thecocktaildb.com\/images\/media\/drink\/wysqut1461867176.jpg",
            "idDrink": "16943"
        },
        {
            "strDrink": "A midsummernight dream",
            "strDrinkThumb": "https:\/\/www.thecocktaildb.com\/images\/media\/drink\/ysqvqp1461867292.jpg",
            "idDrink": "15675"
        },
        {
            "strDrink": "A Night In Old Mandalay",
            "strDrinkThumb": "https:\/\/www.thecocktaildb.com\/images\/media\/drink\/vyrvxt1461919380.jpg",
            "idDrink": "17832"
        },
        {
            "strDrink": "A Piece of Ass",
            "strDrinkThumb": "https:\/\/www.thecocktaildb.com\/images\/media\/drink\/tqxyxx1472719737.jpg",
            "idDrink": "16405"
        },
        {
            "strDrink": "A Splash of Nash",
            "strDrinkThumb": "https:\/\/www.thecocktaildb.com\/images\/media\/drink\/rsvtrr1472668201.jpg",
            "idDrink": "14564"
        },
        {
            "strDrink": "A True Amaretto Sour",
            "strDrinkThumb": "https:\/\/www.thecocktaildb.com\/images\/media\/drink\/rptuxy1472669372.jpg",
            "idDrink": "17005"
        },
        {
            "strDrink": "A. J.",
            "strDrinkThumb": "https:\/\/www.thecocktaildb.com\/images\/media\/drink\/l74qo91582480316.jpg",
            "idDrink": "17833"
        },
        {
            "strDrink": "A.D.M. (After Dinner Mint)",
            "strDrinkThumb": "https:\/\/www.thecocktaildb.com\/images\/media\/drink\/ruxuvp1472669600.jpg",
            "idDrink": "14560"
        },
        {
            "strDrink": "A1",
            "strDrinkThumb": "https:\/\/www.thecocktaildb.com\/images\/media\/drink\/2x8thr1504816928.jpg",
            "idDrink": "17222"
        },
        {
            "strDrink": "Abbey Cocktail",
            "strDrinkThumb": "https:\/\/www.thecocktaildb.com\/images\/media\/drink\/mr30ob1582479875.jpg",
            "idDrink": "17834"
        },
        {
            "strDrink": "Abbey Martini",
            "strDrinkThumb": "https:\/\/www.thecocktaildb.com\/images\/media\/drink\/2mcozt1504817403.jpg",
            "idDrink": "17223"
        },
        {
            "strDrink": "ABC",
            "strDrinkThumb": "https:\/\/www.thecocktaildb.com\/images\/media\/drink\/tqpvqp1472668328.jpg",
            "idDrink": "13501"
        },
        {
            "strDrink": "Abilene",
            "strDrinkThumb": "https:\/\/www.thecocktaildb.com\/images\/media\/drink\/smb2oe1582479072.jpg",
            "idDrink": "17835"
        },
        {
            "strDrink": "Absinthe #2",
            "strDrinkThumb": "https:\/\/www.thecocktaildb.com\/images\/media\/drink\/uxxtrt1472667197.jpg",
            "idDrink": "12790"
        },
        {
            "strDrink": "Absolut Evergreen",
            "strDrinkThumb": "https:\/\/www.thecocktaildb.com\/images\/media\/drink\/wrxrxp1472812609.jpg",
            "idDrink": "14374"
        },
        {
            "strDrink": "Absolut limousine",
            "strDrinkThumb": "https:\/\/www.thecocktaildb.com\/images\/media\/drink\/ssqpyw1472719844.jpg",
            "idDrink": "14372"
        },
        {
            "strDrink": "Absolut Sex",
            "strDrinkThumb": "https:\/\/www.thecocktaildb.com\/images\/media\/drink\/xtrvtx1472668436.jpg",
            "idDrink": "14360"
        },
        {
            "strDrink": "Absolut Stress #2",
            "strDrinkThumb": "https:\/\/www.thecocktaildb.com\/images\/media\/drink\/xuyqrw1472811825.jpg",
            "idDrink": "15597"
        },
        {
            "strDrink": "Absolut Summertime",
            "strDrinkThumb": "https:\/\/www.thecocktaildb.com\/images\/media\/drink\/trpxxs1472669662.jpg",
            "idDrink": "14107"
        },
        {
            "strDrink": "Absolutely Cranberry Smash",
            "strDrinkThumb": "https:\/\/www.thecocktaildb.com\/images\/media\/drink\/vqwstv1472811884.jpg",
            "idDrink": "15024"
        },
        {
            "strDrink": "Absolutely Fabulous",
            "strDrinkThumb": "https:\/\/www.thecocktaildb.com\/images\/media\/drink\/abcpwr1504817734.jpg",
            "idDrink": "17224"
        },
        {
            "strDrink": "Absolutly Screwed Up",
            "strDrinkThumb": "https:\/\/www.thecocktaildb.com\/images\/media\/drink\/yvxrwv1472669728.jpg",
            "idDrink": "16134"
        },
        {
            "strDrink": "Acapulco",
            "strDrinkThumb": "https:\/\/www.thecocktaildb.com\/images\/media\/drink\/il9e0r1582478841.jpg",
            "idDrink": "17836"
        },
        {
            "strDrink": "Ace",
            "strDrinkThumb": "https:\/\/www.thecocktaildb.com\/images\/media\/drink\/l3cd7f1504818306.jpg",
            "idDrink": "17225"
        },
        {
            "strDrink": "ACID",
            "strDrinkThumb": "https:\/\/www.thecocktaildb.com\/images\/media\/drink\/xuxpxt1479209317.jpg",
            "idDrink": "14610"
        },
        {
            "strDrink": "Adam",
            "strDrinkThumb": "https:\/\/www.thecocktaildb.com\/images\/media\/drink\/v0at4i1582478473.jpg",
            "idDrink": "17837"
        },
        {
            "strDrink": "Adam & Eve",
            "strDrinkThumb": "https:\/\/www.thecocktaildb.com\/images\/media\/drink\/vfeumw1504819077.jpg",
            "idDrink": "17226"
        },
        {
            "strDrink": "Adam Bomb",
            "strDrinkThumb": "https:\/\/www.thecocktaildb.com\/images\/media\/drink\/tpxurs1454513016.jpg",
            "idDrink": "16333"
        },
        {
            "strDrink": "Adam Sunrise",
            "strDrinkThumb": "https:\/\/www.thecocktaildb.com\/images\/media\/drink\/vtuyvu1472812112.jpg",
            "idDrink": "15567"
        },
        {
            "strDrink": "Addington",
            "strDrinkThumb": "https:\/\/www.thecocktaildb.com\/images\/media\/drink\/ib0b7g1504818925.jpg",
            "idDrink": "17227"
        },
        {
            "strDrink": "Addison",
            "strDrinkThumb": "https:\/\/www.thecocktaildb.com\/images\/media\/drink\/yzva7x1504820300.jpg",
            "idDrink": "17228"
        },
        {
            "strDrink": "Addison Special",
            "strDrinkThumb": "https:\/\/www.thecocktaildb.com\/images\/media\/drink\/4vo5651493068493.jpg",
            "idDrink": "14272"
        },
        {
            "strDrink": "Adios Amigos Cocktail",
            "strDrinkThumb": "https:\/\/www.thecocktaildb.com\/images\/media\/drink\/8nk2mp1504819893.jpg",
            "idDrink": "17229"
        },
        {
            "strDrink": "Adonis Cocktail",
            "strDrinkThumb": "https:\/\/www.thecocktaildb.com\/images\/media\/drink\/xrvruq1472812030.jpg",
            "idDrink": "17838"
        },
        {
            "strDrink": "Affair",
            "strDrinkThumb": "https:\/\/www.thecocktaildb.com\/images\/media\/drink\/h5za6y1582477994.jpg",
            "idDrink": "17839"
        },
        {
            "strDrink": "Affinity",
            "strDrinkThumb": "https:\/\/www.thecocktaildb.com\/images\/media\/drink\/wzdtnn1582477684.jpg",
            "idDrink": "17840"
        },
        {
            "strDrink": "After Dinner Cocktail",
            "strDrinkThumb": "https:\/\/www.thecocktaildb.com\/images\/media\/drink\/vtytxq1483387578.jpg",
            "idDrink": "11010"
        },
        {
            "strDrink": "After Five",
            "strDrinkThumb": "https:\/\/www.thecocktaildb.com\/images\/media\/drink\/sk3lr91493068595.jpg",
            "idDrink": "13807"
        },
        {
            "strDrink": "After sex",
            "strDrinkThumb": "https:\/\/www.thecocktaildb.com\/images\/media\/drink\/xrl66i1493068702.jpg",
            "idDrink": "15182"
        },
        {
            "strDrink": "After Supper Cocktail",
            "strDrinkThumb": "https:\/\/www.thecocktaildb.com\/images\/media\/drink\/quyxwu1483387610.jpg",
            "idDrink": "11011"
        },
        {
            "strDrink": "Afternoon",
            "strDrinkThumb": "https:\/\/www.thecocktaildb.com\/images\/media\/drink\/vyrurp1472667777.jpg",
            "idDrink": "13162"
        },
        {
            "strDrink": "Alabama Slammer",
            "strDrinkThumb": "https:\/\/www.thecocktaildb.com\/images\/media\/drink\/jntghf1606771886.jpg",
            "idDrink": "11012"
        },
        {
            "strDrink": "Alaska Cocktail",
            "strDrinkThumb": "https:\/\/www.thecocktaildb.com\/images\/media\/drink\/wsyryt1483387720.jpg",
            "idDrink": "11013"
        },
        {
            "strDrink": "Alexander",
            "strDrinkThumb": "https:\/\/www.thecocktaildb.com\/images\/media\/drink\/0clus51606772388.jpg",
            "idDrink": "11014"
        },
        {
            "strDrink": "Alfie Cocktail",
            "strDrinkThumb": "https:\/\/www.thecocktaildb.com\/images\/media\/drink\/ypxsqy1483387829.jpg",
            "idDrink": "11019"
        },
        {
            "strDrink": "Algonquin",
            "strDrinkThumb": "https:\/\/www.thecocktaildb.com\/images\/media\/drink\/uwryxx1483387873.jpg",
            "idDrink": "11020"
        },
        {
            "strDrink": "Alice in Wonderland",
            "strDrinkThumb": "https:\/\/www.thecocktaildb.com\/images\/media\/drink\/g12lj41493069391.jpg",
            "idDrink": "17094"
        },
        {
            "strDrink": "Allegheny",
            "strDrinkThumb": "https:\/\/www.thecocktaildb.com\/images\/media\/drink\/uwvyts1483387934.jpg",
            "idDrink": "11021"
        },
        {
            "strDrink": "Allies Cocktail",
            "strDrinkThumb": "https:\/\/www.thecocktaildb.com\/images\/media\/drink\/qvprvp1483388104.jpg",
            "idDrink": "11022"
        },
        {
            "strDrink": "Almeria",
            "strDrinkThumb": "https:\/\/www.thecocktaildb.com\/images\/media\/drink\/rwsyyu1483388181.jpg",
            "idDrink": "11023"
        },
        {
            "strDrink": "Almond Chocolate Coffee",
            "strDrinkThumb": "https:\/\/www.thecocktaildb.com\/images\/media\/drink\/jls02c1493069441.jpg",
            "idDrink": "16082"
        },
        {
            "strDrink": "Almond Joy",
            "strDrinkThumb": "https:\/\/www.thecocktaildb.com\/images\/media\/drink\/xutuqs1483388296.jpg",
            "idDrink": "11024"
        },
        {
            "strDrink": "Amaretto And Cream",
            "strDrinkThumb": "https:\/\/www.thecocktaildb.com\/images\/media\/drink\/dj8n0r1504375018.jpg",
            "idDrink": "11025"
        },
        {
            "strDrink": "Amaretto fizz",
            "strDrinkThumb": "https:\/\/www.thecocktaildb.com\/images\/media\/drink\/92h3jz1582474310.jpg",
            "idDrink": "178321"
        },
        {
            "strDrink": "Amaretto Liqueur",
            "strDrinkThumb": "https:\/\/www.thecocktaildb.com\/images\/media\/drink\/swqxuv1472719649.jpg",
            "idDrink": "12792"
        },
        {
            "strDrink": "Amaretto Mist",
            "strDrinkThumb": "https:\/\/www.thecocktaildb.com\/images\/media\/drink\/utpxxq1483388370.jpg",
            "idDrink": "11026"
        },
        {
            "strDrink": "Amaretto Rose",
            "strDrinkThumb": "https:\/\/www.thecocktaildb.com\/images\/media\/drink\/3jm41q1493069578.jpg",
            "idDrink": "11027"
        },
        {
            "strDrink": "Amaretto Shake",
            "strDrinkThumb": "https:\/\/www.thecocktaildb.com\/images\/media\/drink\/xk79al1493069655.jpg",
            "idDrink": "15194"
        },
        {
            "strDrink": "Amaretto Sour",
            "strDrinkThumb": "https:\/\/www.thecocktaildb.com\/images\/media\/drink\/xnzc541493070211.jpg",
            "idDrink": "13731"
        },
        {
            "strDrink": "Amaretto Stinger",
            "strDrinkThumb": "https:\/\/www.thecocktaildb.com\/images\/media\/drink\/vvop4w1493069934.jpg",
            "idDrink": "11028"
        },
        {
            "strDrink": "Amaretto Stone Sour",
            "strDrinkThumb": "https:\/\/www.thecocktaildb.com\/images\/media\/drink\/xwryyx1472719921.jpg",
            "idDrink": "14306"
        },
        {
            "strDrink": "Amaretto Stone Sour Alternative",
            "strDrinkThumb": "https:\/\/www.thecocktaildb.com\/images\/media\/drink\/wutxqr1472720012.jpg",
            "idDrink": "16100"
        },
        {
            "strDrink": "Amaretto Sunrise",
            "strDrinkThumb": "https:\/\/www.thecocktaildb.com\/images\/media\/drink\/akcpsh1493070267.jpg",
            "idDrink": "14578"
        },
        {
            "strDrink": "Amaretto Sunset",
            "strDrinkThumb": "https:\/\/www.thecocktaildb.com\/images\/media\/drink\/apictz1493069760.jpg",
            "idDrink": "17168"
        },
        {
            "strDrink": "Amaretto Sweet & Sour",
            "strDrinkThumb": "https:\/\/www.thecocktaildb.com\/images\/media\/drink\/vswwus1472668546.jpg",
            "idDrink": "16202"
        },
        {
            "strDrink": "Amaretto Tea",
            "strDrinkThumb": "https:\/\/www.thecocktaildb.com\/images\/media\/drink\/b7qzo21493070167.jpg",
            "idDrink": "11029"
        },
        {
            "strDrink": "Americano",
            "strDrinkThumb": "https:\/\/www.thecocktaildb.com\/images\/media\/drink\/709s6m1613655124.jpg",
            "idDrink": "15941"
        },
        {
            "strDrink": "Angel Face",
            "strDrinkThumb": "https:\/\/www.thecocktaildb.com\/images\/media\/drink\/vaukir1606772580.jpg",
            "idDrink": "11034"
        },
        {
            "strDrink": "Angelica Liqueur",
            "strDrinkThumb": "https:\/\/www.thecocktaildb.com\/images\/media\/drink\/yuurps1472667672.jpg",
            "idDrink": "12794"
        },
        {
            "strDrink": "Aperol Spritz",
            "strDrinkThumb": "https:\/\/www.thecocktaildb.com\/images\/media\/drink\/iloasq1587661955.jpg",
            "idDrink": "178325"
        },
        {
            "strDrink": "Apple Grande",
            "strDrinkThumb": "https:\/\/www.thecocktaildb.com\/images\/media\/drink\/wqrptx1472668622.jpg",
            "idDrink": "16289"
        },
        {
            "strDrink": "Apple Highball",
            "strDrinkThumb": "https:\/\/www.thecocktaildb.com\/images\/media\/drink\/66mt9b1619695719.jpg",
            "idDrink": "178353"
        },
        {
            "strDrink": "Apple Pie with A Crust",
            "strDrinkThumb": "https:\/\/www.thecocktaildb.com\/images\/media\/drink\/qspqxt1472720078.jpg",
            "idDrink": "16958"
        },
        {
            "strDrink": "Apple Slammer",
            "strDrinkThumb": "https:\/\/www.thecocktaildb.com\/images\/media\/drink\/09yd5f1493069852.jpg",
            "idDrink": "13683"
        },
        {
            "strDrink": "Applecar",
            "strDrinkThumb": "https:\/\/www.thecocktaildb.com\/images\/media\/drink\/sbffau1504389764.jpg",
            "idDrink": "11046"
        },
        {
            "strDrink": "Applejack",
            "strDrinkThumb": "https:\/\/www.thecocktaildb.com\/images\/media\/drink\/sutyqp1479209062.jpg",
            "idDrink": "16311"
        },
        {
            "strDrink": "Apricot Lady",
            "strDrinkThumb": "https:\/\/www.thecocktaildb.com\/images\/media\/drink\/7ityp11582579598.jpg",
            "idDrink": "11050"
        },
        {
            "strDrink": "Apricot punch",
            "strDrinkThumb": "https:\/\/www.thecocktaildb.com\/images\/media\/drink\/tuxxtp1472668667.jpg",
            "idDrink": "15849"
        },
        {
            "strDrink": "Aquamarine",
            "strDrinkThumb": "https:\/\/www.thecocktaildb.com\/images\/media\/drink\/zvsre31572902738.jpg",
            "idDrink": "178319"
        },
        {
            "strDrink": "Archbishop",
            "strDrinkThumb": "https:\/\/www.thecocktaildb.com\/images\/media\/drink\/4g6xds1582579703.jpg",
            "idDrink": "11052"
        },
        {
            "strDrink": "Arctic Fish",
            "strDrinkThumb": "https:\/\/www.thecocktaildb.com\/images\/media\/drink\/ttsvwy1472668781.jpg",
            "idDrink": "14622"
        },
        {
            "strDrink": "Arctic Mouthwash",
            "strDrinkThumb": "https:\/\/www.thecocktaildb.com\/images\/media\/drink\/wqstwv1478963735.jpg",
            "idDrink": "17118"
        }
    ]
}